odoo9_addon_openeducat_assignment-9.0.2.4.0-py2.7-nspkg.pth
odoo_addons/openeducat_assignment/__openerp__.py
odoo_addons/openeducat_assignment/assignment_menu.xml
odoo_addons/openeducat_assignment/__init__.py
odoo_addons/openeducat_assignment/security/ir.model.access.csv
odoo_addons/openeducat_assignment/dashboard/assignment_student_dashboard.xml
odoo_addons/openeducat_assignment/dashboard/assignment_faculty_dashboard.xml
odoo_addons/openeducat_assignment/models/assignment_type.py
odoo_addons/openeducat_assignment/models/assignment.py
odoo_addons/openeducat_assignment/models/__init__.py
odoo_addons/openeducat_assignment/models/student.py
odoo_addons/openeducat_assignment/models/assignment_sub_line.py
odoo_addons/openeducat_assignment/i18n/openeducat_assignment.pot
odoo_addons/openeducat_assignment/views/assignment_view.xml
odoo_addons/openeducat_assignment/views/assignment_type_view.xml
odoo_addons/openeducat_assignment/views/student_view.xml
odoo_addons/openeducat_assignment/views/assignment_sub_line_view.xml
odoo_addons/openeducat_assignment/demo/op.assignment.type.csv
odoo_addons/openeducat_assignment/demo/op.assignment.sub.line.csv
odoo_addons/openeducat_assignment/demo/op.assignment.csv
odoo_addons/openeducat_assignment/static/description/openeducat_logo.png
odoo_addons/openeducat_assignment/static/description/assignment.png
odoo_addons/openeducat_assignment/static/description/openeducat_assignment_banner.jpg
odoo_addons/openeducat_assignment/static/description/assignment_submission.png
odoo_addons/openeducat_assignment/static/description/index.html
odoo_addons/openeducat_assignment/static/description/icon.png
odoo9_addon_openeducat_assignment-9.0.2.4.0.dist-info/top_level.txt
odoo9_addon_openeducat_assignment-9.0.2.4.0.dist-info/WHEEL
odoo9_addon_openeducat_assignment-9.0.2.4.0.dist-info/RECORD
odoo9_addon_openeducat_assignment-9.0.2.4.0.dist-info/metadata.json
odoo9_addon_openeducat_assignment-9.0.2.4.0.dist-info/DESCRIPTION.rst
odoo9_addon_openeducat_assignment-9.0.2.4.0.dist-info/METADATA
odoo9_addon_openeducat_assignment-9.0.2.4.0.dist-info/namespace_packages.txt
